polylith/alias/__init__.py
polylith/alias/core.py
polylith/bricks/__init__.py
polylith/bricks/base.py
polylith/bricks/brick.py
polylith/bricks/component.py
polylith/check/__init__.py
polylith/check/collect.py
polylith/check/grouping.py
polylith/check/report.py
polylith/commands/__init__.py
polylith/commands/check.py
polylith/commands/create.py
polylith/commands/deps.py
polylith/commands/diff.py
polylith/commands/info.py
polylith/commands/libs.py
polylith/commands/sync.py
polylith/commands/test.py
polylith/configuration/__init__.py
polylith/configuration/core.py
polylith/deps/__init__.py
polylith/deps/core.py
polylith/deps/report.py
polylith/development/__init__.py
polylith/development/development.py
polylith/diff/__init__.py
polylith/diff/collect.py
polylith/diff/report.py
polylith/dirs/__init__.py
polylith/dirs/dirs.py
polylith/distributions/__init__.py
polylith/distributions/caching.py
polylith/distributions/collect.py
polylith/distributions/core.py
polylith/files/__init__.py
polylith/files/files.py
polylith/imports/__init__.py
polylith/imports/parser.py
polylith/info/__init__.py
polylith/info/collect.py
polylith/info/report.py
polylith/interactive/__init__.py
polylith/interactive/project.py
polylith/interface/__init__.py
polylith/interface/interfaces.py
polylith/libs/__init__.py
polylith/libs/grouping.py
polylith/libs/lock_files.py
polylith/libs/report.py
polylith/libs/stdlib.py
polylith/output/__init__.py
polylith/output/core.py
polylith/poetry/__init__.py
polylith/poetry/commands/__init__.py
polylith/poetry/commands/check.py
polylith/poetry/commands/command_options.py
polylith/poetry/commands/create_base.py
polylith/poetry/commands/create_component.py
polylith/poetry/commands/create_project.py
polylith/poetry/commands/create_workspace.py
polylith/poetry/commands/deps.py
polylith/poetry/commands/diff.py
polylith/poetry/commands/info.py
polylith/poetry/commands/libs.py
polylith/poetry/commands/sync.py
polylith/poetry/commands/test.py
polylith/poetry/internals.py
poetry_polylith_plugin-1.47.1.dist-info/METADATA
poetry_polylith_plugin-1.47.1.dist-info/WHEEL
poetry_polylith_plugin-1.47.1.dist-info/entry_points.txt
poetry_polylith_plugin-1.47.1.dist-info/RECORD
