Metadata-Version: 2.4
Name: poetry-polylith-plugin
Version: 1.47.1
Summary: A Poetry plugin that adds tooling support for the Polylith Architecture
License: MIT
Author: David Vujic
Requires-Python: >=3.8,<4.0
Classifier: License :: OSI Approved :: MIT License
Classifier: Programming Language :: Python :: 3
Classifier: Programming Language :: Python :: 3.8
Classifier: Programming Language :: Python :: 3.9
Classifier: Programming Language :: Python :: 3.10
Classifier: Programming Language :: Python :: 3.11
Classifier: Programming Language :: Python :: 3.12
Classifier: Programming Language :: Python :: 3.13
Classifier: Programming Language :: Python :: 3.14
Requires-Dist: cleo (>=2.1.0,<3.0.0)
Requires-Dist: poetry
Requires-Dist: pyyaml
Requires-Dist: rich (>=13,<15)
Requires-Dist: tomlkit (==0.*)
Project-URL: Homepage, https://davidvujic.github.io/python-polylith-docs/
Project-URL: Repository, https://github.com/davidvujic/python-polylith
